cpu.v
// ============================================================
// NOVA-64 CPU — Verilog RTL (Register Transfer Level)
//
// Hedef   : Herhangi bir FPGA (Xilinx, Intel/Altera, Lattice)
// Sentez  : Xilinx Vivado / Intel Quartus / Yosys (açık kaynak)
//
// Mimari  : 64-bit veri yolu, 32 register, sabit 32-bit komut
//           (tek kelime = tek komut, sim.c/asm.c/dbg.c ile birebir uyumlu)
// Bellek  : Harici SRAM/Block-RAM (port üzerinden), 65536 kelime,
//           16-bit kelime adresi (adres yolu genişliği veri yolundan bağımsız)
// Pipeline: Yok (tek döngülü fetch-decode-execute)
// ============================================================

`timescale 1ns / 1ps

module nova32_cpu (
    // ── Saat ve Sıfırlama ───────────────────────────────
    input  wire        clk,      // sistem saati
    input  wire        rst_n,    // aktif-düşük asenkron sıfırlama

    // ── Bellek Arayüzü ──────────────────────────────────
    // Tek portlu, 64-bit word-addressed bellek (65536 kelime → 16-bit adres)
    // mem_addr/mem_we/mem_wdata KOMBİNASYONELDİR (senkron SRAM'e doğrudan
    // sürülür); mem_rdata bir sonraki saat kenarında geçerli olur.
    output reg  [15:0] mem_addr,  // bellek adresi (kelime)
    output reg         mem_we,    // write enable
    output reg  [63:0] mem_wdata, // yazılacak veri (64-bit)
    input  wire [63:0] mem_rdata, // okunan veri (64-bit)

    // ── G/Ç Arayüzü ─────────────────────────────────────
    output reg  [7:0]  io_addr,   // port numarası
    output reg         io_we,     // port yazma
    output reg  [63:0] io_wdata,  // yazılacak port verisi (64-bit)
    input  wire [63:0] io_rdata,  // okunan port verisi (64-bit)

    // ── Durum Çıkışları ──────────────────────────────────
    output reg         halted,    // HALT komutu çalıştı
    output reg  [63:0] cycles     // çalıştırılan komut sayısı (64-bit)
);

// ─── Opcode Sabitleri ────────────────────────────────────
localparam OP_NOP    = 6'h00;
localparam OP_ADD    = 6'h01;
localparam OP_SUB    = 6'h02;
localparam OP_AND    = 6'h03;
localparam OP_OR     = 6'h04;
localparam OP_XOR    = 6'h05;
localparam OP_SHL    = 6'h06;
localparam OP_SHR    = 6'h07;
localparam OP_LOAD   = 6'h08;
localparam OP_STORE  = 6'h09;
localparam OP_LI     = 6'h0A;
localparam OP_JMP    = 6'h0B;
localparam OP_JZ     = 6'h0C;
localparam OP_JNZ    = 6'h0D;
localparam OP_CALL   = 6'h0E;
localparam OP_RET    = 6'h0F;
localparam OP_OUT    = 6'h10;
localparam OP_IN     = 6'h11;
localparam OP_MUL    = 6'h1A;
localparam OP_DIV    = 6'h1B;
localparam OP_RFLAGS = 6'h1C;
localparam OP_HALT   = 6'h3F;

// ─── Durum Makinesi ─────────────────────────────────────
//
// NOVA-64'de her komut TEK 32-bit kelime olduğundan fetch tek adımda
// yapılır. mem_addr KOMBİNASYONEL olarak sürülür (registered değil),
// böylece senkron bellek bir sonraki saat kenarında doğru veriyi
// mem_rdata'ya yazar:
//
//   FETCH     → mem_addr = pc  (kombinasyonel)         → mem_rdata bir
//               sonraki kenarda mem[pc] olur
//   EXECUTE   → mem_rdata artık komut kelimesi; decode + çalıştır.
//               LOAD/STORE/CALL/RET için mem_addr yine kombinasyonel
//               olarak bu döngüde sürülür.
//   LOAD_WAIT / RET_WAIT / IN_WAIT → LOAD, RET ve IN için ek okuma
//               bekleme adımı (adres/istek EXECUTE'ta gönderilir,
//               veri bir döngü sonra mem_rdata/io_rdata'da hazır olur)
//
localparam S_FETCH     = 3'd0;
localparam S_EXECUTE   = 3'd1;
localparam S_LOAD_WAIT = 3'd2;
localparam S_RET_WAIT  = 3'd3;
localparam S_IN_WAIT   = 3'd4;

reg [2:0] state;

// ─── Register Dosyası ────────────────────────────────────
// regs[0] her zaman 0 (yazma yoksayılır)
reg [63:0] regs [0:31];

// ─── Dahili Sinyaller ────────────────────────────────────
reg [15:0] pc;          // program counter (kelime adresi)
reg [4:0]  wb_dest;     // LOAD/IN tamamlanınca yazılacak hedef register

// ─── Register Yazma Yardımcısı (R0 korumalı) ────────────
task write_reg;
    input [4:0]  rn;
    input [63:0] val;
    begin
        if (rn != 5'd0)
            regs[rn] <= val;
    end
endtask

// ─── Komut Alanları (EXECUTE'ta mem_rdata[31:0] = geçerli komut) ───
// Komut 32-bit; 64-bit bellek kelimesinin alt 32 bitinde saklanır.
wire [31:0] insn    = mem_rdata[31:0];
wire [5:0]  op      = insn[31:26];
wire [4:0]  fd      = insn[25:21];
wire [4:0]  fa      = insn[20:16];
wire [4:0]  fb      = insn[15:11];
wire [10:0] raw_imm = insn[10:0];
wire signed [63:0] imm_s = {{53{raw_imm[10]}}, raw_imm};  // 11→64 bit işaret uzatma

wire [63:0] rv_fd = (fd == 5'd0) ? 64'd0 : regs[fd];
wire [63:0] rv_fa = (fa == 5'd0) ? 64'd0 : regs[fa];
wire [63:0] rv_fb = (fb == 5'd0) ? 64'd0 : regs[fb];

wire [15:0] next_pc     = pc + 16'd1;            // fetch sonrası PC
wire [15:0] branch_dst  = next_pc + imm_s[15:0]; // göreli dal hedefi
wire [15:0] mem_eff     = rv_fa[15:0] + imm_s[15:0]; // LOAD/STORE efektif adres

// ─── Kombinasyonel Bellek/G-Ç Yolu Sürücüsü ─────────────
always @(*) begin
    mem_addr  = pc;
    mem_we    = 1'b0;
    mem_wdata = 64'd0;
    io_addr   = 8'd0;
    io_we     = 1'b0;
    io_wdata  = 64'd0;

    case (state)
        S_FETCH: mem_addr = pc;

        S_EXECUTE: begin
            case (op)
                OP_LOAD:  mem_addr = mem_eff;
                OP_STORE: begin
                    mem_addr  = mem_eff;
                    mem_we    = 1'b1;
                    mem_wdata = rv_fd;
                end
                OP_CALL: begin
                    mem_addr  = regs[7][15:0] - 16'd1; // yeni R7 (push)
                    mem_we    = 1'b1;
                    mem_wdata = {48'd0, next_pc};
                end
                OP_RET:  mem_addr = regs[7][15:0];     // mevcut R7 (pop)
                OP_OUT: begin
                    io_addr  = raw_imm[7:0];
                    io_we    = 1'b1;
                    io_wdata = rv_fd;
                end
                OP_IN:   io_addr = raw_imm[7:0];
                default: ;
            endcase
        end

        default: ; // LOAD_WAIT/RET_WAIT/IN_WAIT: adres önemsiz
    endcase
end

// ─── Ana Durum Makinesi ──────────────────────────────────
integer i;

always @(posedge clk or negedge rst_n) begin
    if (!rst_n) begin
        // ── Sıfırlama ──
        state   <= S_FETCH;
        pc      <= 16'd0;
        halted  <= 1'b0;
        cycles  <= 64'd0;
        wb_dest <= 5'd0;
        for (i = 0; i < 32; i = i + 1)
            regs[i] <= 64'd0;
    end
    else if (!halted) begin

        case (state)

            // ────────────────────────────────────────────
            // FETCH — mem_addr (kombinasyonel) = pc gönderildi;
            // bir sonraki döngüde mem_rdata geçerli olacak.
            // ────────────────────────────────────────────
            S_FETCH: state <= S_EXECUTE;

            // ────────────────────────────────────────────
            // EXECUTE — Komutu çalıştır (mem_rdata[31:0] = komut)
            // ────────────────────────────────────────────
            S_EXECUTE: begin
                pc     <= pc + 16'd1;   // varsayılan ilerleme (dallanma override eder)
                cycles <= cycles + 64'd1;
                state  <= S_FETCH;      // varsayılan; LOAD/RET/IN override eder

                case (op)
                    OP_NOP: ; // hiçbir şey yapma

                    OP_HALT: halted <= 1'b1;

                    OP_ADD: write_reg(fd, $signed(rv_fa) + $signed(rv_fb));
                    OP_SUB: write_reg(fd, $signed(rv_fa) - $signed(rv_fb));
                    OP_AND: write_reg(fd, rv_fa & rv_fb);
                    OP_OR:  write_reg(fd, rv_fa | rv_fb);
                    OP_XOR: write_reg(fd, rv_fa ^ rv_fb);

                    OP_SHL: write_reg(fd, rv_fa << raw_imm[5:0]);
                    OP_SHR: write_reg(fd, rv_fa >> raw_imm[5:0]);

                    OP_LI: write_reg(fd, imm_s);

                    OP_MUL: write_reg(fd, $signed(rv_fa) * $signed(rv_fb));

                    OP_DIV: begin
                        if (rv_fb == 64'd0)
                            write_reg(fd, 64'd0);
                        else
                            write_reg(fd, $signed(rv_fa) / $signed(rv_fb));
                    end

                    OP_RFLAGS: write_reg(fd, 64'd0); // basitleştirilmiş RTL: bayrak reg. yok

                    OP_LOAD: begin
                        // RD = mem[RA + IMM]; adres bu döngüde kombinasyonel gönderildi
                        wb_dest <= fd;
                        state   <= S_LOAD_WAIT;
                    end

                    OP_STORE: ; // mem[RA+IMM] = RD; yazma bu döngüde kombinasyonel yapıldı

                    OP_JMP:  pc <= branch_dst;
                    OP_JZ:   if (rv_fd == 64'd0) pc <= branch_dst;
                    OP_JNZ:  if (rv_fd != 64'd0) pc <= branch_dst;

                    OP_CALL: begin
                        // R7--; mem[yeni R7] = PC_next (bu döngüde kombinasyonel yazıldı); PC = hedef
                        regs[7] <= regs[7] - 64'd1;
                        pc      <= branch_dst;
                    end

                    OP_RET: begin
                        // PC = mem[R7] (bir sonraki döngüde hazır); R7++
                        regs[7] <= regs[7] + 64'd1;
                        state   <= S_RET_WAIT;
                    end

                    OP_OUT: ; // io_wdata bu döngüde kombinasyonel yazıldı

                    OP_IN: begin
                        // io_addr bu döngüde kombinasyonel gönderildi
                        wb_dest <= fd;
                        state   <= S_IN_WAIT;
                    end

                    default: halted <= 1'b1;  // geçersiz opcode
                endcase
            end // S_EXECUTE

            // ────────────────────────────────────────────
            // LOAD_WAIT — mem_rdata artık okunan değer (64-bit)
            // ────────────────────────────────────────────
            S_LOAD_WAIT: begin
                write_reg(wb_dest, mem_rdata);
                state <= S_FETCH;
            end

            // ────────────────────────────────────────────
            // RET_WAIT — mem_rdata artık dönüş adresi (alt 16 bit)
            // ────────────────────────────────────────────
            S_RET_WAIT: begin
                pc    <= mem_rdata[15:0];
                state <= S_FETCH;
            end

            // ────────────────────────────────────────────
            // IN_WAIT — io_rdata artık okunan port verisi (64-bit)
            // ────────────────────────────────────────────
            S_IN_WAIT: begin
                write_reg(wb_dest, io_rdata);
                state <= S_FETCH;
            end

        endcase
    end // !halted
end

endmodule


// ============================================================
// Test Bench — nova32_cpu_tb.v
// Icarus Verilog ile çalıştır:
//   iverilog -o sim_tb cpu.v -DTESTBENCH && vvp sim_tb
// ============================================================
`ifdef TESTBENCH

module nova32_cpu_tb;

    reg        clk;
    reg        rst_n;
    wire [15:0] mem_addr;
    wire        mem_we;
    wire [63:0] mem_wdata;
    reg  [63:0] mem_rdata;
    wire [7:0]  io_addr;
    wire        io_we;
    wire [63:0] io_wdata;
    reg  [63:0] io_rdata;
    wire        halted;
    wire [63:0] cycles;

    // ── CPU örneği ──────────────────────────────────────
    nova32_cpu uut (
        .clk      (clk),
        .rst_n    (rst_n),
        .mem_addr (mem_addr),
        .mem_we   (mem_we),
        .mem_wdata(mem_wdata),
        .mem_rdata(mem_rdata),
        .io_addr  (io_addr),
        .io_we    (io_we),
        .io_wdata (io_wdata),
        .io_rdata (io_rdata),
        .halted   (halted),
        .cycles   (cycles)
    );

    // ── Bellek modeli (256 kelime, 64-bit) ───────────────
    reg [63:0] sim_mem [0:255];
    integer    ii;

    always @(posedge clk) begin
        mem_rdata <= sim_mem[mem_addr[7:0]];
        if (mem_we)
            sim_mem[mem_addr[7:0]] <= mem_wdata;
    end

    // ── G/Ç modeli ───────────────────────────────────────
    reg [63:0] io_ports [0:255];
    always @(posedge clk) begin
        io_rdata <= io_ports[io_addr];
        if (io_we) begin
            io_ports[io_addr] <= io_wdata;
            $display("[OUT] port[%0d] = %0d", io_addr, io_wdata);
        end
    end

    // ── Saat üreteci (10ns periyot = 100 MHz) ───────────
    initial clk = 0;
    always #5 clk = ~clk;

    // ── Test: 1..10 toplama ──────────────────────────────
    //
    // Test programı (test.bin içeriği tek 32-bit kelime/komut):
    //   opcode[31:26] d[25:21] a[20:16] b[15:11] imm11[10:0]
    //
    //   0x00: LI  R1, 1
    //   0x01: LI  R2, 11
    //   0x02: LI  R3, 0
    //   0x03: LI  R4, 1
    //   0x04: ADD R3, R3, R1
    //   0x05: ADD R1, R1, R4
    //   0x06: SUB R5, R1, R2
    //   0x07: JNZ R5, -4   (pc+1 sonrası -4 → adres 0x04'e döner)
    //   0x08: OUT R3, 0
    //   0x09: HALT
    //
    localparam OP_ADD=6'h01, OP_SUB=6'h02, OP_LI=6'h0A, OP_JNZ=6'h0D,
               OP_OUT=6'h10, OP_HALT=6'h3F;

    function [31:0] enc;
        input [5:0]  op;
        input [4:0]  d, a, b;
        input [10:0] imm;
        begin
            enc = {op, d, a, b, imm};
        end
    endfunction

    initial begin
        // Bellek ve portları sıfırla
        for (ii = 0; ii < 256; ii = ii + 1) begin
            sim_mem[ii]  = 64'h0;
            io_ports[ii] = 64'h0;
        end

        // Test programını belleğe yükle (komutlar 64-bit kelimenin alt 32 bitinde)
        // Yeni format: [31:26]=op [25:21]=fd [20:16]=fa [15:11]=fb [10:0]=imm11
        sim_mem[0] = {32'd0, enc(OP_LI,  5'd1, 5'd0, 5'd0, 11'd1)};    // LI R1, 1
        sim_mem[1] = {32'd0, enc(OP_LI,  5'd2, 5'd0, 5'd0, 11'd11)};   // LI R2, 11
        sim_mem[2] = {32'd0, enc(OP_LI,  5'd3, 5'd0, 5'd0, 11'd0)};    // LI R3, 0
        sim_mem[3] = {32'd0, enc(OP_LI,  5'd4, 5'd0, 5'd0, 11'd1)};    // LI R4, 1
        sim_mem[4] = {32'd0, enc(OP_ADD, 5'd3, 5'd3, 5'd1, 11'd0)};    // ADD R3,R3,R1
        sim_mem[5] = {32'd0, enc(OP_ADD, 5'd1, 5'd1, 5'd4, 11'd0)};    // ADD R1,R1,R4
        sim_mem[6] = {32'd0, enc(OP_SUB, 5'd5, 5'd1, 5'd2, 11'd0)};    // SUB R5,R1,R2
        sim_mem[7] = {32'd0, enc(OP_JNZ, 5'd5, 5'd0, 5'd0, 11'h7FC)};  // JNZ R5, -4
        sim_mem[8] = {32'd0, enc(OP_OUT, 5'd3, 5'd0, 5'd0, 11'd0)};    // OUT R3, 0
        sim_mem[9] = {32'd0, enc(OP_HALT,5'd0, 5'd0, 5'd0, 11'd0)};    // HALT

        // Sıfırlama
        rst_n = 0;
        #20;
        rst_n = 1;

        // HALT bekle (max 500 döngü)
        for (ii = 0; ii < 500; ii = ii + 1) begin
            @(posedge clk);
            if (halted) begin
                #10;
                $display("-----------------------------------");
                $display("NOVA-64 Verilog Simülasyonu Tamam");
                $display("Cycles  : %0d", cycles);
                $display("Halted  : %b", halted);
                $display("port[0] : %0d (beklenen: 55)", io_ports[0]);
                if (io_ports[0] == 64'd55)
                    $display("TEST GECTI \u2713");
                else
                    $display("TEST BASARISIZ \u2717");
                $display("-----------------------------------");
                $finish;
            end
        end

        $display("ZAMAN ASIMI — CPU durmadi!");
        $finish;
    end

    // VCD dalga formu kaydı (GTKWave ile görüntülenebilir)
    initial begin
        $dumpfile("nova32_wave.vcd");
        $dumpvars(0, nova32_cpu_tb);
    end

endmodule

`endif

nova32_wave.vcd
$date
	Fri Jul 10 10:33:30 2026
$end
$version
	Icarus Verilog
$end
$timescale
	1ps
$end
$scope module nova32_cpu_tb $end
$var wire 1 ! mem_we $end
$var wire 64 " mem_wdata [63:0] $end
$var wire 16 # mem_addr [15:0] $end
$var wire 1 $ io_we $end
$var wire 64 % io_wdata [63:0] $end
$var wire 8 & io_addr [7:0] $end
$var wire 1 ' halted $end
$var wire 64 ( cycles [63:0] $end
$var parameter 6 ) OP_ADD $end
$var parameter 6 * OP_HALT $end
$var parameter 6 + OP_JNZ $end
$var parameter 6 , OP_LI $end
$var parameter 6 - OP_OUT $end
$var parameter 6 . OP_SUB $end
$var reg 1 / clk $end
$var reg 64 0 io_rdata [63:0] $end
$var reg 64 1 mem_rdata [63:0] $end
$var reg 1 2 rst_n $end
$var integer 32 3 ii [31:0] $end
$scope function enc $end
$var reg 5 4 a [4:0] $end
$var reg 5 5 b [4:0] $end
$var reg 5 6 d [4:0] $end
$var reg 11 7 imm [10:0] $end
$var reg 6 8 op [5:0] $end
$upscope $end
$scope module uut $end
$var wire 1 / clk $end
$var wire 64 9 io_rdata [63:0] $end
$var wire 64 : mem_rdata [63:0] $end
$var wire 1 2 rst_n $end
$var wire 64 ; rv_fd [63:0] $end
$var wire 64 < rv_fb [63:0] $end
$var wire 64 = rv_fa [63:0] $end
$var wire 11 > raw_imm [10:0] $end
$var wire 6 ? op [5:0] $end
$var wire 16 @ next_pc [15:0] $end
$var wire 16 A mem_eff [15:0] $end
$var wire 32 B insn [31:0] $end
$var wire 64 C imm_s [63:0] $end
$var wire 5 D fd [4:0] $end
$var wire 5 E fb [4:0] $end
$var wire 5 F fa [4:0] $end
$var wire 16 G branch_dst [15:0] $end
$var parameter 6 H OP_ADD $end
$var parameter 6 I OP_AND $end
$var parameter 6 J OP_CALL $end
$var parameter 6 K OP_DIV $end
$var parameter 6 L OP_HALT $end
$var parameter 6 M OP_IN $end
$var parameter 6 N OP_JMP $end
$var parameter 6 O OP_JNZ $end
$var parameter 6 P OP_JZ $end
$var parameter 6 Q OP_LI $end
$var parameter 6 R OP_LOAD $end
$var parameter 6 S OP_MUL $end
$var parameter 6 T OP_NOP $end
$var parameter 6 U OP_OR $end
$var parameter 6 V OP_OUT $end
$var parameter 6 W OP_RET $end
$var parameter 6 X OP_RFLAGS $end
$var parameter 6 Y OP_SHL $end
$var parameter 6 Z OP_SHR $end
$var parameter 6 [ OP_STORE $end
$var parameter 6 \ OP_SUB $end
$var parameter 6 ] OP_XOR $end
$var parameter 3 ^ S_EXECUTE $end
$var parameter 3 _ S_FETCH $end
$var parameter 3 ` S_IN_WAIT $end
$var parameter 3 a S_LOAD_WAIT $end
$var parameter 3 b S_RET_WAIT $end
$var reg 64 c cycles [63:0] $end
$var reg 1 ' halted $end
$var reg 8 d io_addr [7:0] $end
$var reg 64 e io_wdata [63:0] $end
$var reg 1 $ io_we $end
$var reg 16 f mem_addr [15:0] $end
$var reg 64 g mem_wdata [63:0] $end
$var reg 1 ! mem_we $end
$var reg 16 h pc [15:0] $end
$var reg 3 i state [2:0] $end
$var reg 5 j wb_dest [4:0] $end
$var integer 32 k i [31:0] $end
$scope task write_reg $end
$var reg 5 l rn [4:0] $end
$var reg 64 m val [63:0] $end
$upscope $end
$upscope $end
$upscope $end
$enddefinitions $end
$comment Show the parameter values. $end
$dumpall
b11 b
b10 a
b100 `
b0 _
b1 ^
b101 ]
b10 \
b1001 [
b111 Z
b110 Y
b11100 X
b1111 W
b10000 V
b100 U
b0 T
b11010 S
b1000 R
b1010 Q
b1100 P
b1101 O
b1011 N
b10001 M
b111111 L
b11011 K
b1110 J
b11 I
b1 H
b10 .
b10000 -
b1010 ,
b1101 +
b111111 *
b1 )
$end
#0
$dumpvars
bx m
bx l
b100000 k
b0 j
b0 i
b0 h
b0 g
b0 f
b0 e
b0 d
b0 c
bx G
bx F
bx E
bx D
bx C
bx B
bx A
b1 @
bx ?
bx >
bx =
bx <
bx ;
bx :
bx 9
b111111 8
b0 7
b0 6
b0 5
b0 4
b100000000 3
02
bx 1
bx 0
0/
b0 (
0'
b0 &
b0 %
0$
b0 #
b0 "
0!
$end
#5000
b1 A
b10 G
b0 ;
b0 =
b0 <
b1010 ?
b1 D
b0 F
b0 E
b1 C
b1 >
b101000001000000000000000000001 B
b101000001000000000000000000001 1
b101000001000000000000000000001 :
b0 0
b0 9
b100000 k
1/
#10000
0/
#15000
b100000 k
1/
#20000
0/
b0 3
12
#25000
b1 i
b1 3
1/
#30000
0/
#35000
b1 ;
b1 #
b1 f
b0 i
b1 (
b1 c
b11 G
b10 @
b1 h
b1 m
b1 l
b10 3
1/
#40000
0/
#45000
b0 ;
b1101 G
b1011 A
b10 D
b1011 C
b1011 >
b101000010000000000000000001011 B
b1 i
b101000010000000000000000001011 1
b101000010000000000000000001011 :
b11 3
1/
#50000
0/
#55000
b1011 ;
b10 #
b10 f
b0 i
b10 (
b10 c
b1110 G
b11 @
b10 h
b1011 m
b10 l
b100 3
1/
#60000
0/
#65000
b0 ;
b11 G
b0 A
b11 D
b0 C
b0 >
b101000011000000000000000000000 B
b1 i
b101000011000000000000000000000 1
b101000011000000000000000000000 :
b101 3
1/
#70000
0/
#75000
b11 #
b11 f
b0 i
b11 (
b11 c
b100 G
b100 @
b11 h
b0 m
b11 l
b110 3
1/
#80000
0/
#85000
b101 G
b1 A
b100 D
b1 C
b1 >
b101000100000000000000000000001 B
b1 i
b101000100000000000000000000001 1
b101000100000000000000000000001 :
b111 3
1/
#90000
0/
#95000
b1 ;
b100 #
b100 f
b0 i
b100 (
b100 c
b110 G
b101 @
b100 h
b1 m
b100 l
b1000 3
1/
#100000
0/
#105000
b0 ;
b1 <
b101 G
b0 A
b1 ?
b11 D
b11 F
b1 E
b0 C
b0 >
b100011000110000100000000000 B
b1 i
b100011000110000100000000000 1
b100011000110000100000000000 :
b1001 3
1/
#110000
0/
#115000
b1 A
b1 ;
b1 =
b101 #
b101 f
b0 i
b101 (
b101 c
b110 G
b110 @
b101 h
b11 l
b1010 3
1/
#120000
0/
#125000
b1 D
b1 F
b100 E
b100001000010010000000000000 B
b1 i
b100001000010010000000000000 1
b100001000010010000000000000 :
b1011 3
1/
#130000
0/
#135000
b10 A
b10 ;
b10 =
b110 #
b110 f
b0 i
b110 (
b110 c
b111 G
b111 @
b110 h
b10 m
b1 l
b1100 3
1/
#140000
0/
#145000
b0 ;
b1011 <
b10 ?
b101 D
b10 E
b1000101000010001000000000000 B
b1 i
b1000101000010001000000000000 1
b1000101000010001000000000000 :
b1101 3
1/
#150000
0/
#155000
b1111111111111111111111111111111111111111111111111111111111110111 ;
b111 #
b111 f
b0 i
b111 (
b111 c
b1000 G
b1000 @
b111 h
b1111111111111111111111111111111111111111111111111111111111110111 m
b101 l
b1110 3
1/
#160000
0/
#165000
b0 =
b0 <
b100 G
b1111111111111100 A
b1101 ?
b0 F
b0 E
b1111111111111111111111111111111111111111111111111111111111111100 C
b11111111100 >
b110100101000000000011111111100 B
b1 i
b110100101000000000011111111100 1
b110100101000000000011111111100 :
b1111 3
1/
#170000
0/
#175000
b100 #
b100 f
b0 i
b1000 (
b1000 c
b1 G
b101 @
b100 h
b10000 3
1/
#180000
0/
#185000
b1 ;
b1 =
b10 <
b101 G
b1 A
b1 ?
b11 D
b11 F
b1 E
b0 C
b0 >
b100011000110000100000000000 B
b1 i
b100011000110000100000000000 1
b100011000110000100000000000 :
b10001 3
1/
#190000
0/
#195000
b11 A
b11 ;
b11 =
b101 #
b101 f
b0 i
b1001 (
b1001 c
b110 G
b110 @
b101 h
b11 m
b11 l
b10010 3
1/
#200000
0/
#205000
b10 A
b10 ;
b10 =
b1 <
b1 D
b1 F
b100 E
b100001000010010000000000000 B
b1 i
b100001000010010000000000000 1
b100001000010010000000000000 :
b10011 3
1/
#210000
0/
#215000
b11 A
b11 ;
b11 =
b110 #
b110 f
b0 i
b1010 (
b1010 c
b111 G
b111 @
b110 h
b1 l
b10100 3
1/
#220000
0/
#225000
b1111111111111111111111111111111111111111111111111111111111110111 ;
b1011 <
b10 ?
b101 D
b10 E
b1000101000010001000000000000 B
b1 i
b1000101000010001000000000000 1
b1000101000010001000000000000 :
b10101 3
1/
#230000
0/
#235000
b1111111111111111111111111111111111111111111111111111111111111000 ;
b111 #
b111 f
b0 i
b1011 (
b1011 c
b1000 G
b1000 @
b111 h
b1111111111111111111111111111111111111111111111111111111111111000 m
b101 l
b10110 3
1/
#240000
0/
#245000
b0 =
b0 <
b100 G
b1111111111111100 A
b1101 ?
b0 F
b0 E
b1111111111111111111111111111111111111111111111111111111111111100 C
b11111111100 >
b110100101000000000011111111100 B
b1 i
b110100101000000000011111111100 1
b110100101000000000011111111100 :
b10111 3
1/
#250000
0/
#255000
b100 #
b100 f
b0 i
b1100 (
b1100 c
b1 G
b101 @
b100 h
b11000 3
1/
#260000
0/
#265000
b11 ;
b11 =
b11 <
b101 G
b11 A
b1 ?
b11 D
b11 F
b1 E
b0 C
b0 >
b100011000110000100000000000 B
b1 i
b100011000110000100000000000 1
b100011000110000100000000000 :
b11001 3
1/
#270000
0/
#275000
b110 A
b110 ;
b110 =
b101 #
b101 f
b0 i
b1101 (
b1101 c
b110 G
b110 @
b101 h
b110 m
b11 l
b11010 3
1/
#280000
0/
#285000
b11 A
b11 ;
b11 =
b1 <
b1 D
b1 F
b100 E
b100001000010010000000000000 B
b1 i
b100001000010010000000000000 1
b100001000010010000000000000 :
b11011 3
1/
#290000
0/
#295000
b100 A
b100 ;
b100 =
b110 #
b110 f
b0 i
b1110 (
b1110 c
b111 G
b111 @
b110 h
b100 m
b1 l
b11100 3
1/
#300000
0/
#305000
b1111111111111111111111111111111111111111111111111111111111111000 ;
b1011 <
b10 ?
b101 D
b10 E
b1000101000010001000000000000 B
b1 i
b1000101000010001000000000000 1
b1000101000010001000000000000 :
b11101 3
1/
#310000
0/
#315000
b1111111111111111111111111111111111111111111111111111111111111001 ;
b111 #
b111 f
b0 i
b1111 (
b1111 c
b1000 G
b1000 @
b111 h
b1111111111111111111111111111111111111111111111111111111111111001 m
b101 l
b11110 3
1/
#320000
0/
#325000
b0 =
b0 <
b100 G
b1111111111111100 A
b1101 ?
b0 F
b0 E
b1111111111111111111111111111111111111111111111111111111111111100 C
b11111111100 >
b110100101000000000011111111100 B
b1 i
b110100101000000000011111111100 1
b110100101000000000011111111100 :
b11111 3
1/
#330000
0/
#335000
b100 #
b100 f
b0 i
b10000 (
b10000 c
b1 G
b101 @
b100 h
b100000 3
1/
#340000
0/
#345000
b110 ;
b110 =
b100 <
b101 G
b110 A
b1 ?
b11 D
b11 F
b1 E
b0 C
b0 >
b100011000110000100000000000 B
b1 i
b100011000110000100000000000 1
b100011000110000100000000000 :
b100001 3
1/
#350000
0/
#355000
b1010 A
b1010 ;
b1010 =
b101 #
b101 f
b0 i
b10001 (
b10001 c
b110 G
b110 @
b101 h
b1010 m
b11 l
b100010 3
1/
#360000
0/
#365000
b100 A
b100 ;
b100 =
b1 <
b1 D
b1 F
b100 E
b100001000010010000000000000 B
b1 i
b100001000010010000000000000 1
b100001000010010000000000000 :
b100011 3
1/
#370000
0/
#375000
b101 A
b101 ;
b101 =
b110 #
b110 f
b0 i
b10010 (
b10010 c
b111 G
b111 @
b110 h
b101 m
b1 l
b100100 3
1/
#380000
0/
#385000
b1111111111111111111111111111111111111111111111111111111111111001 ;
b1011 <
b10 ?
b101 D
b10 E
b1000101000010001000000000000 B
b1 i
b1000101000010001000000000000 1
b1000101000010001000000000000 :
b100101 3
1/
#390000
0/
#395000
b1111111111111111111111111111111111111111111111111111111111111010 ;
b111 #
b111 f
b0 i
b10011 (
b10011 c
b1000 G
b1000 @
b111 h
b1111111111111111111111111111111111111111111111111111111111111010 m
b101 l
b100110 3
1/
#400000
0/
#405000
b0 =
b0 <
b100 G
b1111111111111100 A
b1101 ?
b0 F
b0 E
b1111111111111111111111111111111111111111111111111111111111111100 C
b11111111100 >
b110100101000000000011111111100 B
b1 i
b110100101000000000011111111100 1
b110100101000000000011111111100 :
b100111 3
1/
#410000
0/
#415000
b100 #
b100 f
b0 i
b10100 (
b10100 c
b1 G
b101 @
b100 h
b101000 3
1/
#420000
0/
#425000
b1010 ;
b1010 =
b101 <
b101 G
b1010 A
b1 ?
b11 D
b11 F
b1 E
b0 C
b0 >
b100011000110000100000000000 B
b1 i
b100011000110000100000000000 1
b100011000110000100000000000 :
b101001 3
1/
#430000
0/
#435000
b1111 A
b1111 ;
b1111 =
b101 #
b101 f
b0 i
b10101 (
b10101 c
b110 G
b110 @
b101 h
b1111 m
b11 l
b101010 3
1/
#440000
0/
#445000
b101 A
b101 ;
b101 =
b1 <
b1 D
b1 F
b100 E
b100001000010010000000000000 B
b1 i
b100001000010010000000000000 1
b100001000010010000000000000 :
b101011 3
1/
#450000
0/
#455000
b110 A
b110 ;
b110 =
b110 #
b110 f
b0 i
b10110 (
b10110 c
b111 G
b111 @
b110 h
b110 m
b1 l
b101100 3
1/
#460000
0/
#465000
b1111111111111111111111111111111111111111111111111111111111111010 ;
b1011 <
b10 ?
b101 D
b10 E
b1000101000010001000000000000 B
b1 i
b1000101000010001000000000000 1
b1000101000010001000000000000 :
b101101 3
1/
#470000
0/
#475000
b1111111111111111111111111111111111111111111111111111111111111011 ;
b111 #
b111 f
b0 i
b10111 (
b10111 c
b1000 G
b1000 @
b111 h
b1111111111111111111111111111111111111111111111111111111111111011 m
b101 l
b101110 3
1/
#480000
0/
#485000
b0 =
b0 <
b100 G
b1111111111111100 A
b1101 ?
b0 F
b0 E
b1111111111111111111111111111111111111111111111111111111111111100 C
b11111111100 >
b110100101000000000011111111100 B
b1 i
b110100101000000000011111111100 1
b110100101000000000011111111100 :
b101111 3
1/
#490000
0/
#495000
b100 #
b100 f
b0 i
b11000 (
b11000 c
b1 G
b101 @
b100 h
b110000 3
1/
#500000
0/
#505000
b1111 ;
b1111 =
b110 <
b101 G
b1111 A
b1 ?
b11 D
b11 F
b1 E
b0 C
b0 >
b100011000110000100000000000 B
b1 i
b100011000110000100000000000 1
b100011000110000100000000000 :
b110001 3
1/
#510000
0/
#515000
b10101 A
b10101 ;
b10101 =
b101 #
b101 f
b0 i
b11001 (
b11001 c
b110 G
b110 @
b101 h
b10101 m
b11 l
b110010 3
1/
#520000
0/
#525000
b110 A
b110 ;
b110 =
b1 <
b1 D
b1 F
b100 E
b100001000010010000000000000 B
b1 i
b100001000010010000000000000 1
b100001000010010000000000000 :
b110011 3
1/
#530000
0/
#535000
b111 A
b111 ;
b111 =
b110 #
b110 f
b0 i
b11010 (
b11010 c
b111 G
b111 @
b110 h
b111 m
b1 l
b110100 3
1/
#540000
0/
#545000
b1111111111111111111111111111111111111111111111111111111111111011 ;
b1011 <
b10 ?
b101 D
b10 E
b1000101000010001000000000000 B
b1 i
b1000101000010001000000000000 1
b1000101000010001000000000000 :
b110101 3
1/
#550000
0/
